openg2p_g2p_bridge_celery_beat_producers/__init__.py
openg2p_g2p_bridge_celery_beat_producers/app.py
openg2p_g2p_bridge_celery_beat_producers/config.py
openg2p_g2p_bridge_celery_beat_producers/tasks/__init__.py
openg2p_g2p_bridge_celery_beat_producers/tasks/block_funds_with_bank.py
openg2p_g2p_bridge_celery_beat_producers/tasks/check_funds_with_bank_task.py
openg2p_g2p_bridge_celery_beat_producers/tasks/disburse_funds_from_bank.py
openg2p_g2p_bridge_celery_beat_producers/tasks/mapper_resolution_task.py
openg2p_g2p_bridge_celery_beat_producers/tasks/mt940_processor.py
openg2p_g2p_bridge_celery_beat_producers-1.0.2.dist-info/METADATA
openg2p_g2p_bridge_celery_beat_producers-1.0.2.dist-info/WHEEL
openg2p_g2p_bridge_celery_beat_producers-1.0.2.dist-info/RECORD
